gamemode.abi3.so
pygamemode-0.1.2.dist-info/top_level.txt
pygamemode-0.1.2.dist-info/WHEEL
pygamemode-0.1.2.dist-info/LICENSE
pygamemode-0.1.2.dist-info/METADATA
pygamemode-0.1.2.dist-info/RECORD
