Metadata-Version: 2.1
Name: pygamemode
Version: 0.1.2
Summary: A Python wrapper for the GameMode client API.
Home-page: https://github.com/aforren1/pygamemode
Author: Alexander Forrence
Author-email: alex.forrence@gmail.com
License: BSD 3
Platform: UNKNOWN
Classifier: Development Status :: 4 - Beta
Classifier: Operating System :: POSIX :: Linux
Classifier: Intended Audience :: Developers
Classifier: License :: OSI Approved :: BSD License
Classifier: Programming Language :: Python :: 3
Classifier: Topic :: Multimedia :: Graphics
Classifier: Topic :: Scientific/Engineering :: Visualization
License-File: LICENSE
